PuppeteerLibrary/__init__.py
PuppeteerLibrary/_version.py
PuppeteerLibrary/base/__init__.py
PuppeteerLibrary/base/context.py
PuppeteerLibrary/base/ipuppeteer_library.py
PuppeteerLibrary/base/librarycomponent.py
PuppeteerLibrary/base/robotlibcore.py
PuppeteerLibrary/custom_elements/SPage.py
PuppeteerLibrary/custom_elements/__init__.py
PuppeteerLibrary/custom_elements/base_page.py
PuppeteerLibrary/ikeywords/__init__.py
PuppeteerLibrary/ikeywords/base_async_keywords.py
PuppeteerLibrary/ikeywords/ialert_async.py
PuppeteerLibrary/ikeywords/ibrowsermanagement_async.py
PuppeteerLibrary/ikeywords/icheckbox_async.py
PuppeteerLibrary/ikeywords/idropdown_async.py
PuppeteerLibrary/ikeywords/ielement_async.py
PuppeteerLibrary/ikeywords/iformelement_async.py
PuppeteerLibrary/ikeywords/ijavascript_async.py
PuppeteerLibrary/ikeywords/imockresponse_async.py
PuppeteerLibrary/ikeywords/imouseevent_async.py
PuppeteerLibrary/ikeywords/ipdf_async.py
PuppeteerLibrary/ikeywords/iscreenshot_async.py
PuppeteerLibrary/ikeywords/iwaiting_async.py
PuppeteerLibrary/keywords/__init__.py
PuppeteerLibrary/keywords/alert.py
PuppeteerLibrary/keywords/browsermanagement.py
PuppeteerLibrary/keywords/checkbox.py
PuppeteerLibrary/keywords/dropdown.py
PuppeteerLibrary/keywords/element.py
PuppeteerLibrary/keywords/formelement.py
PuppeteerLibrary/keywords/javascript.py
PuppeteerLibrary/keywords/mockresponse.py
PuppeteerLibrary/keywords/mouseevent.py
PuppeteerLibrary/keywords/pdf.py
PuppeteerLibrary/keywords/screenshot.py
PuppeteerLibrary/keywords/utility.py
PuppeteerLibrary/keywords/waiting.py
PuppeteerLibrary/library_context/__init__.py
PuppeteerLibrary/library_context/ilibrary_context.py
PuppeteerLibrary/library_context/library_context_factory.py
PuppeteerLibrary/locators/ChainLocatorParser.py
PuppeteerLibrary/locators/CssLocatorParser.py
PuppeteerLibrary/locators/IdLocatorParser.py
PuppeteerLibrary/locators/LinkLocatorParser.py
PuppeteerLibrary/locators/LocatorParserImplementation.py
robotframework_PuppeteerLibrary-3.1.10.dist-info/LICENSE
robotframework_PuppeteerLibrary-3.1.10.dist-info/METADATA
robotframework_PuppeteerLibrary-3.1.10.dist-info/WHEEL
robotframework_PuppeteerLibrary-3.1.10.dist-info/top_level.txt
robotframework_PuppeteerLibrary-3.1.10.dist-info/RECORD
