Metadata-Version: 2.1
Name: robotframework-PuppeteerLibrary
Version: 3.1.10
Summary: PuppeteerLibrary is a Web Testing library for Robot Framework.
Home-page: https://qahive.github.io/robotframework-puppeteer.github.io/
Author: QA Hive Co.,Ltd
Author-email: support@qahive.com
License: Apache License 2.0
Keywords: robotframework puppeteer web-testing automation
Platform: any
Classifier: Programming Language :: Python :: 3
Classifier: Programming Language :: Python :: 3.7
Classifier: Programming Language :: Python :: 3.8
Classifier: Programming Language :: Python :: 3.9
Classifier: License :: OSI Approved :: Apache Software License
Classifier: Operating System :: OS Independent
Classifier: Topic :: Software Development :: Testing
Classifier: Topic :: Software Development :: Testing :: Acceptance
Classifier: Framework :: Robot Framework
Requires-Python: >3.6
License-File: LICENSE
Requires-Dist: robotframework (>=3.2.1)
Requires-Dist: playwright (==1.22.0)
Requires-Dist: pyppeteer (==1.0.2)
